astblick/__init__.py
astblick/favicon.ico
astblick/style.css
astblick-0.9.8.1.data/scripts/astblick-repo
astblick-0.9.8.1.data/scripts/astblickd
astblick-0.9.8.1.dist-info/LICENSE.txt
astblick-0.9.8.1.dist-info/METADATA
astblick-0.9.8.1.dist-info/WHEEL
astblick-0.9.8.1.dist-info/top_level.txt
astblick-0.9.8.1.dist-info/RECORD
